timit_utils/__init__.py
timit_utils/audio_utils.py
timit_utils/basic_utils.py
timit_utils/core.py
timit_utils/drawing_utils.py
timit_utils-0.9.0.dist-info/LICENSE
timit_utils-0.9.0.dist-info/METADATA
timit_utils-0.9.0.dist-info/WHEEL
timit_utils-0.9.0.dist-info/top_level.txt
timit_utils-0.9.0.dist-info/RECORD
