Metadata-Version: 2.1
Name: timit-utils
Version: 0.9.0
Summary: A convenience python wrapper for the TIMIT database.
Home-page: https://github.com/colinator/timit_utils
Author: Colin Prepscius
Author-email: colinprepscius@gmail.com
License: UNKNOWN
Platform: UNKNOWN
Classifier: Programming Language :: Python :: 3
Classifier: License :: OSI Approved :: MIT License
Classifier: Operating System :: OS Independent
Requires-Dist: numpy
Requires-Dist: pandas
Requires-Dist: scipy
Requires-Dist: matplotlib
Requires-Dist: python-speech-features
Requires-Dist: SoundFile (>=0.8.0)
